<?xml version='1.0' encoding='UTF-8'?>
<song xmlns="http://openlyrics.info/namespace/2009/song" version="0.8" createdIn="OpenLP 2.4" modifiedIn="OpenLP 2.4" modifiedDate="2017-01-14T20:54:30">
  <properties>
    <titles>
      <title>Ni Nini Kitanizuia</title>
    </titles>
    <verseOrder>c1 v1 c1 v2 c1 v3 c1</verseOrder>
    <authors>
      <author>Communion</author>
    </authors>
  </properties>
  <lyrics>
    <verse name="c1">
      <lines>Ni nini kitanizuia,<br/>ni nini kitanizuia mimi. x2<br/>Nisiende mbele ya meza<br/>kumpokea Bwana. x2</lines>
    </verse>
    <verse name="v1">
      <lines>Kama uwongo we <br/>jifikirie mwenyewe,<br/>jifikirie.<br/>Kama ni uzushi we <br/>jifikirie mwenyewe,<br/>jifikirie.</lines>
    </verse>
    <verse name="v2">
      <lines>Kama ni unyang'anyi we <br/>jifikirie mwenyewe,<br/>jifikirie.<br/>Kama ni ulevi we <br/>jifikirie mwenyewe,<br/>jifikirie.</lines>
    </verse>
    <verse name="v3">
      <lines>Kama ni uzinzi we <br/>jifikirie mwenyewe,<br/>jifikirie.<br/>Kama ni uchafu we <br/>jifikirie mwenyewe,<br/>jifikirie.</lines>
    </verse>
  </lyrics>
</song>
