<?xml version='1.0' encoding='UTF-8'?>
<song xmlns="http://openlyrics.info/namespace/2009/song" version="0.8" createdIn="OpenLP 2.4" modifiedIn="OpenLP 2.4" modifiedDate="2017-01-14T20:52:52">
  <properties>
    <titles>
      <title>Bwana Mungu Aliona</title>
    </titles>
    <verseOrder>v1 c1 v2 c1 v3 c1</verseOrder>
    <authors>
      <author>Christmas</author>
    </authors>
  </properties>
  <lyrics>
    <verse name="v1">
      <lines>Bwana Mungu aliona <br/>Mwanakondoo apotea.<br/>Kwa upendo akamtoa, <br/>Mwana wake wa pekee.</lines>
    </verse>
    <verse name="c1">
      <lines>Alelu - aleluya kazaliwa<br/>Yesu mwa - Yesu Mwana wa Pekee<br/>Bethlehe - Bethlehemu amelazwa<br/>Mama - Mamayo Maryamu.</lines>
    </verse>
    <verse name="v2">
      <lines>Lile neno lilikuwa <br/>maandishi yanenavyo.<br/>Na kwa yeye vitu <br/>vyote vikapata kuwepo.</lines>
    </verse>
    <verse name="v3">
      <lines>Siku Yesu alizaliwa <br/>watu wote walishangilia.<br/>Wakasema huyu mfalme <br/>Mwokozi wa dunia.</lines>
    </verse>
  </lyrics>
</song>
